<estimates_list>
  <estimate>
    <estimate_id>5</estimate_id>
    <client_id>2</client_id>
    <expiration_date>26/11/2020-00:00:00</expiration_date>
    <insert_date>25/11/2020-20:15:43</insert_date>
    <item_groups_list>
      <item_group>
        <items_list>
          <item>
            <description>prova</description>
            <unity_of_measure></unity_of_measure>
            <quantity>0.0</quantity>
            <price>0.0</price>
            <tax_rate>
              <tax_value>22.0</tax_value>
              <tax_description>Ordinaria</tax_description>
            </tax_rate>
            <discount>0.0</discount>
          </item>
        </items_list>
        <items_list>
          <item>
            <description>prova2</description>
            <unity_of_measure></unity_of_measure>
            <quantity>1.0</quantity>
            <price>0.0</price>
            <tax_rate>
              <tax_value>22.0</tax_value>
              <tax_description>Ordinaria</tax_description>
            </tax_rate>
            <discount>0.0</discount>
          </item>
        </items_list>
      </item_group>
    </item_groups_list>
    <deposit>0.0</deposit>
  </estimate>
  <estimate>
    <estimate_id>5</estimate_id>
    <client_id>2</client_id>
    <expiration_date>26/11/2020-00:00:00</expiration_date>
    <insert_date>25/11/2020-20:15:43</insert_date>
    <item_groups_list></item_groups_list>
    <deposit>0.0</deposit>
  </estimate>
</estimates_list>
